README.txt
setup.py
s_sudoku/__init__.py
s_sudoku.egg-info/PKG-INFO
s_sudoku.egg-info/SOURCES.txt
s_sudoku.egg-info/dependency_links.txt
s_sudoku.egg-info/top_level.txt