Metadata-Version: 1.1
Name: s-sudoku
Version: 0.0.1
Summary: Sudoku solver
Home-page: UNKNOWN
Author: Kushagar Goel
Author-email: kushagargoel28@gmail.com
License: MIT
Keywords: sudoku
Platform: UNKNOWN
Classifier: Development Status :: 5 - Production/Stable
Classifier: Intended Audience :: Education
Classifier: Operating System :: Microsoft :: Windows :: Windows 10
Classifier: License :: OSI Approved :: MIT License
Classifier: Programming Language :: Python :: 3
